odoo8_addon_partner_contact_in_several_companies-8.0.1.0.0.99.dev10-py2.7-nspkg.pth
odoo8_addon_partner_contact_in_several_companies-8.0.1.0.0.99.dev10.dist-info/METADATA
odoo8_addon_partner_contact_in_several_companies-8.0.1.0.0.99.dev10.dist-info/RECORD
odoo8_addon_partner_contact_in_several_companies-8.0.1.0.0.99.dev10.dist-info/WHEEL
odoo8_addon_partner_contact_in_several_companies-8.0.1.0.0.99.dev10.dist-info/namespace_packages.txt
odoo8_addon_partner_contact_in_several_companies-8.0.1.0.0.99.dev10.dist-info/top_level.txt
odoo_addons/partner_contact_in_several_companies/README.rst
odoo_addons/partner_contact_in_several_companies/__init__.py
odoo_addons/partner_contact_in_several_companies/__openerp__.py
odoo_addons/partner_contact_in_several_companies/models.py
odoo_addons/partner_contact_in_several_companies/demo/res_partner.xml
odoo_addons/partner_contact_in_several_companies/i18n/de.po
odoo_addons/partner_contact_in_several_companies/i18n/es.po
odoo_addons/partner_contact_in_several_companies/i18n/eu.po
odoo_addons/partner_contact_in_several_companies/i18n/fi.po
odoo_addons/partner_contact_in_several_companies/i18n/fr.po
odoo_addons/partner_contact_in_several_companies/i18n/it.po
odoo_addons/partner_contact_in_several_companies/i18n/nl.po
odoo_addons/partner_contact_in_several_companies/i18n/partner_contact_in_several_companies.pot
odoo_addons/partner_contact_in_several_companies/i18n/sl.po
odoo_addons/partner_contact_in_several_companies/static/description/icon.png
odoo_addons/partner_contact_in_several_companies/tests/__init__.py
odoo_addons/partner_contact_in_several_companies/tests/test_partner_contact_in_several_companies.py
odoo_addons/partner_contact_in_several_companies/views/res_partner.xml
